cnvrg/__init__.py
cnvrg/main.py
cnvrg/version.py
cnvrg/actions/__init__.py
cnvrg/actions/experiment_actions.py
cnvrg/actions/global_actions.py
cnvrg/actions/project_actions.py
cnvrg/actions/status_helpers.py
cnvrg/actions/file_actions/__init__.py
cnvrg/charts/__init__.py
cnvrg/charts/pandas_analyzer.py
cnvrg/helpers/__init__.py
cnvrg/helpers/apis_helper.py
cnvrg/helpers/args_helper.py
cnvrg/helpers/async_runner.py
cnvrg/helpers/auth_helper.py
cnvrg/helpers/chart_show_helper.py
cnvrg/helpers/cli_helper.py
cnvrg/helpers/clone_helper.py
cnvrg/helpers/cnvrgignore_helper.py
cnvrg/helpers/config_helper.py
cnvrg/helpers/control_stdout_helper.py
cnvrg/helpers/crypto_helpers.py
cnvrg/helpers/data_working_dir_helper.py
cnvrg/helpers/env_helper.py
cnvrg/helpers/error_catcher.py
cnvrg/helpers/export_library_helper.py
cnvrg/helpers/files_helper.py
cnvrg/helpers/hash_helper.py
cnvrg/helpers/hyper_search_helper.py
cnvrg/helpers/libs_helper.py
cnvrg/helpers/logger_helper.py
cnvrg/helpers/parallel_helper.py
cnvrg/helpers/param_build_helper.py
cnvrg/helpers/param_helper.py
cnvrg/helpers/random_helper.py
cnvrg/helpers/spawn_helper.py
cnvrg/helpers/status_helpers.py
cnvrg/helpers/string_helper.py
cnvrg/helpers/time_helper.py
cnvrg/helpers/url_builder_helper.py
cnvrg/libs/__init__.py
cnvrg/libs/limit/__init__.py
cnvrg/modules/__init__.py
cnvrg/modules/base_module.py
cnvrg/modules/cnvrg_files.py
cnvrg/modules/cnvrg_job.py
cnvrg/modules/cnvrg_keras_callback.py
cnvrg/modules/cnvrg_me.py
cnvrg/modules/commituploader.py
cnvrg/modules/data_loader.py
cnvrg/modules/dataset.py
cnvrg/modules/endpoint.py
cnvrg/modules/endpoint_version_data.py
cnvrg/modules/errors.py
cnvrg/modules/experiment.py
cnvrg/modules/flow.py
cnvrg/modules/flow_version.py
cnvrg/modules/grid.py
cnvrg/modules/library.py
cnvrg/modules/project.py
cnvrg/modules/data_connector/__init__.py
cnvrg/modules/data_connector/base_connector.py
cnvrg/modules/data_connector/files_connector/__init__.py
cnvrg-0.7.55.dist-info/METADATA
cnvrg-0.7.55.dist-info/WHEEL
cnvrg-0.7.55.dist-info/entry_points.txt
cnvrg-0.7.55.dist-info/top_level.txt
cnvrg-0.7.55.dist-info/RECORD
