Metadata-Version: 2.1
Name: cnvrg
Version: 0.7.55
Summary: UNKNOWN
Home-page: UNKNOWN
Author: cnvrg
Author-email: support@cnvrg.io
License: UNKNOWN
Platform: UNKNOWN
Requires-Python: >3.5
Requires-Dist: click
Requires-Dist: requests (==2.23.0)
Requires-Dist: boto3
Requires-Dist: colorama
Requires-Dist: tqdm
Requires-Dist: pyaml
Requires-Dist: tinynetrc
Requires-Dist: pycryptodome
Requires-Dist: psutil
Requires-Dist: dill
Requires-Dist: pytz
Requires-Dist: numpy
Requires-Dist: pandas
Requires-Dist: azure-core (==1.10.0)
Requires-Dist: azure-storage-blob (==12.6.0)
Requires-Dist: google-cloud-storage
Requires-Dist: six (>=1.13)
Requires-Dist: progress
Requires-Dist: croniter
